dummyzarid/__init__.py
tests/__init__.py
tests/test_dummyzarid.py
dummyzarid-0.0.4.dist-info/METADATA
dummyzarid-0.0.4.dist-info/WHEEL
dummyzarid-0.0.4.dist-info/top_level.txt
dummyzarid-0.0.4.dist-info/RECORD
