Metadata-Version: 2.1
Name: dummyzarid
Version: 0.0.4
Summary: Generate dummy South African ID numbers
Home-page: https://github.com/teamgeek-io/dummyzarid
Author: Teamgeek
Author-email: support@teamgeek.io
License: UNKNOWN
Platform: UNKNOWN
Classifier: Programming Language :: Python :: 3
Classifier: License :: OSI Approved :: MIT License
Classifier: Operating System :: OS Independent
Requires-Python: >=3.6
Requires-Dist: requests (==2.23.0)
